scryfall/__init__.py
scryfall-0.1.0.dist-info/LICENSE
scryfall-0.1.0.dist-info/METADATA
scryfall-0.1.0.dist-info/WHEEL
scryfall-0.1.0.dist-info/RECORD
