Metadata-Version: 2.1
Name: scryfall
Version: 0.1.0
Summary: Python SDK for Scryfall
License: MIT
Author: ThatDevShparki
Author-email: shparki@thatdev.io
Requires-Python: >=3.10,<4.0
Classifier: License :: OSI Approved :: MIT License
Classifier: Programming Language :: Python :: 3
Classifier: Programming Language :: Python :: 3.10
Classifier: Programming Language :: Python :: 3.11
Classifier: Programming Language :: Python :: 3.12
Classifier: Programming Language :: Python :: 3.13
